sqlmiddleware/__init__.py
sqlmiddleware/globals.py
sqlmiddleware/middlewares.py
sqlmiddleware/urls.py
sqlmiddleware/views.py
sqlmiddleware/static/sqlmiddleware/css/bootstrap.min.css
sqlmiddleware/static/sqlmiddleware/css/monokai-sublime.css
sqlmiddleware/static/sqlmiddleware/css/theme.css
sqlmiddleware/static/sqlmiddleware/js/bootstrap.bundle.min.js
sqlmiddleware/static/sqlmiddleware/js/highlight.pack.js
sqlmiddleware/static/sqlmiddleware/js/jquery-3.4.1.min.js
sqlmiddleware/static/sqlmiddleware/js/sql-formatter.min.js
sqlmiddleware/templates/sqlmiddleware/detail.html
sqlmiddleware/templates/sqlmiddleware/index.html
sqlmiddleware/templates/sqlmiddleware/layout.html
django_sql_middleware-0.0.7.dist-info/LICENSE
django_sql_middleware-0.0.7.dist-info/METADATA
django_sql_middleware-0.0.7.dist-info/WHEEL
django_sql_middleware-0.0.7.dist-info/top_level.txt
django_sql_middleware-0.0.7.dist-info/RECORD
