Metadata-Version: 2.1
Name: django-sql-middleware
Version: 0.0.7
Summary: Simple SQL Middleware for Django
Home-page: https://github.com/fatanugraha/django-sql-middleware
Author: Fata Nugraha
Author-email: fatanugraha@outlook.com
License: UNKNOWN
Platform: UNKNOWN
Classifier: Programming Language :: Python :: 3
Classifier: License :: OSI Approved :: MIT License
Classifier: Operating System :: OS Independent
Requires-Python: >=3.6
Requires-Dist: django
